drf_nested_relations-0.0.2.dist-info/DESCRIPTION.rst
drf_nested_relations-0.0.2.dist-info/METADATA
drf_nested_relations-0.0.2.dist-info/RECORD
drf_nested_relations-0.0.2.dist-info/WHEEL
drf_nested_relations-0.0.2.dist-info/metadata.json
drf_nested_relations-0.0.2.dist-info/top_level.txt
nested_relations/__init__.py
nested_relations/apps.py
nested_relations/decorators.py
nested_relations/serializers.py
nested_relations/tests.py
